omop_cdm/__init__.py
omop_cdm/constants.py
omop_cdm/dynamic/cdm531/__init__.py
omop_cdm/dynamic/cdm531/clinical_data.py
omop_cdm/dynamic/cdm531/derived_elements.py
omop_cdm/dynamic/cdm531/health_economics.py
omop_cdm/dynamic/cdm531/health_system_data.py
omop_cdm/dynamic/cdm531/metadata.py
omop_cdm/dynamic/cdm531/vocabularies.py
omop_cdm/dynamic/cdm54/__init__.py
omop_cdm/dynamic/cdm54/clinical_data.py
omop_cdm/dynamic/cdm54/derived_elements.py
omop_cdm/dynamic/cdm54/health_economics.py
omop_cdm/dynamic/cdm54/health_system_data.py
omop_cdm/dynamic/cdm54/metadata.py
omop_cdm/dynamic/cdm54/vocabularies/__init__.py
omop_cdm/dynamic/cdm54/vocabularies/vocabularies.py
omop_cdm/dynamic/cdm600/__init__.py
omop_cdm/dynamic/cdm600/clinical_data.py
omop_cdm/dynamic/cdm600/derived_elements.py
omop_cdm/dynamic/cdm600/health_economics.py
omop_cdm/dynamic/cdm600/health_system_data.py
omop_cdm/dynamic/cdm600/metadata.py
omop_cdm/dynamic/cdm600/vocabularies.py
omop_cdm/dynamic/legacy/__init__.py
omop_cdm/dynamic/legacy/legacy.py
omop_cdm/dynamic/ruff.toml
omop_cdm/regular/cdm531/__init__.py
omop_cdm/regular/cdm531/tables.py
omop_cdm/regular/cdm54/__init__.py
omop_cdm/regular/cdm54/tables.py
omop_cdm/regular/cdm600/__init__.py
omop_cdm/regular/cdm600/tables.py
omop_cdm/regular/ruff.toml
omop_cdm/util.py
omop_cdm-0.4.3.dist-info/METADATA
omop_cdm-0.4.3.dist-info/WHEEL
omop_cdm-0.4.3.dist-info/licenses/LICENSE
omop_cdm-0.4.3.dist-info/RECORD
