Metadata-Version: 2.4
Name: omop-cdm
Version: 0.4.3
Summary: SQLAlchemy ORM of the OHDSI OMOP CDM
License: Apache Software License
License-File: LICENSE
Author: Spayralbe
Author-email: stefan@thehyve.nl
Requires-Python: >=3.9.2,<4.0
Classifier: Intended Audience :: Developers
Classifier: Operating System :: OS Independent
Classifier: Development Status :: 4 - Beta
Classifier: Natural Language :: English
Classifier: License :: OSI Approved :: Apache Software License
Classifier: Programming Language :: Python :: 3
Classifier: Programming Language :: Python :: 3.9
Classifier: Programming Language :: Python :: 3.10
Classifier: Programming Language :: Python :: 3.11
Classifier: Programming Language :: Python :: 3.12
Classifier: Programming Language :: Python :: 3.13
Classifier: Programming Language :: Python :: 3.14
Classifier: Programming Language :: Python :: Implementation :: CPython
Requires-Dist: sqlalchemy (>=2.0.41,<3.0.0)
Project-URL: Bug Tracker, https://github.com/thehyve/omop-cdm/issues
Project-URL: Changelog, https://github.com/thehyve/omop-cdm/blob/main/CHANGELOG.md
Project-URL: Documentation, https://github.com/thehyve/omop-cdm/blob/main/docs/README.md
Project-URL: Repository, https://github.com/thehyve/omop-cdm
